flaskcbv/__init__.py
flaskcbv/request.py
flaskcbv/response.py
flaskcbv/version.py
flaskcbv/conf/__init__.py
flaskcbv/conf/defaults.py
flaskcbv/core/__init__.py
flaskcbv/core/base.py
flaskcbv/forms/__init__.py
flaskcbv/forms/form.py
flaskcbv/protos/custom/apps/__init__.py
flaskcbv/protos/custom/apps/flaskconfig.py
flaskcbv/protos/custom/apps/project.py
flaskcbv/protos/custom/apps/start.py
flaskcbv/protos/custom/apps/urls.py
flaskcbv/protos/custom/apps/main/__init__.py
flaskcbv/protos/custom/apps/main/urls.py
flaskcbv/protos/custom/apps/main/views.py
flaskcbv/protos/custom/apps/main/templates/main/index-ajax.tpl
flaskcbv/protos/custom/misc/__init__.py
flaskcbv/protos/custom/misc/httpexceptions.py
flaskcbv/protos/custom/misc/mixins/__init__.py
flaskcbv/protos/custom/settings/__init__.py
flaskcbv/protos/custom/settings/local.py
flaskcbv/protos/custom/templates/index.tpl
flaskcbv/protos/custom/templates/misc/static.tpl
flaskcbv/protos/simple/apps/__init__.py
flaskcbv/protos/simple/apps/flaskconfig.py
flaskcbv/protos/simple/apps/project.py
flaskcbv/protos/simple/apps/start.py
flaskcbv/protos/simple/apps/urls.py
flaskcbv/protos/simple/apps/main/__init__.py
flaskcbv/protos/simple/apps/main/urls.py
flaskcbv/protos/simple/apps/main/views.py
flaskcbv/protos/simple/apps/main/templates/main/index.tpl
flaskcbv/protos/simple/settings/__init__.py
flaskcbv/protos/simple/settings/local.py
flaskcbv/scripts/__init__.py
flaskcbv/scripts/cliargs.py
flaskcbv/scripts/common.py
flaskcbv/scripts/flaskcbv.py
flaskcbv/scripts/commands/__init__.py
flaskcbv/scripts/commands/initproject.py
flaskcbv/scripts/commands/startapp.py
flaskcbv/templates/__init__.py
flaskcbv/templatetags/__init__.py
flaskcbv/url/__init__.py
flaskcbv/view/__init__.py
flaskcbv/view/crud.py
flaskcbv/view/generic.py
flaskcbv/view/mixins/__init__.py
flaskcbv/view/mixins/getargument.py
flaskcbv/view/mixins/jsonmixin.py
flaskcbv-1.5.7.dist-info/LICENSE
flaskcbv-1.5.7.dist-info/METADATA
flaskcbv-1.5.7.dist-info/WHEEL
flaskcbv-1.5.7.dist-info/entry_points.txt
flaskcbv-1.5.7.dist-info/top_level.txt
flaskcbv-1.5.7.dist-info/RECORD
