Metadata-Version: 2.1
Name: flaskcbv
Version: 1.5.7
Summary: FlaskCBV is Alternative Framework for working with flask with the class Based Views approach (CBV)
Home-page: https://github.com/procool/flaskcbv/
Author: procool
Author-email: ya.procool@ya.ru
License: BSD 2 Clause
Platform: UNKNOWN
Classifier: Programming Language :: Python :: 3.8
Requires-Python: >=3.6
Requires-Dist: Flask
Requires-Dist: Werkzeug (==2.0.0)
Requires-Dist: setuptools
